amhhandler/__init__.py
amhhandler/cfgutils.py
amhhandler/drobot.py
amhhandler/logger.py
amhhandler/mysql.py
amhhandler/shell.py
amhhandler-1.2.9.dist-info/LICENSE
amhhandler-1.2.9.dist-info/METADATA
amhhandler-1.2.9.dist-info/WHEEL
amhhandler-1.2.9.dist-info/top_level.txt
amhhandler-1.2.9.dist-info/RECORD
