Metadata-Version: 2.1
Name: amhhandler
Version: 1.2.9
Summary: An even better way to work with Python.
Home-page: https://gitee.com/nbyue/amh-handler
Author: nbyue
Author-email: 20671413@163.com
License: MIT
Classifier: Development Status :: 4 - Beta
Classifier: Programming Language :: Python :: 3
Classifier: License :: OSI Approved :: MIT License
Classifier: Operating System :: OS Independent
Requires-Python: >=3.6
License-File: LICENSE
Requires-Dist: pymysql
Requires-Dist: requests
